[
  {
    "state": "Madhyapradesh",
    "hospitalName": "LATE SHRI NATTULALJI MORI MEMORIAL HOSPITAL SANAWAD",
    "hospitalAdress": "Not Available",
    "district": "khargone",
    "phoneNo": "9425279142",
    "oxygenBedTotal": "-",
    "oxygenBedOccupied": "-",
    "oxygenBedAvailable": "0",
    "normalBedTotal": "-",
    "normalBedOccupied": "-",
    "normalBedAvailable": "-",
    "lastUpdatedDate": "25-05-2021",
    "lastUpdatedTime": " 18:54:31",
    "googleSearch": "https://www.google.com/search?q=LATE+SHRI NATTULALJI MORI MEMORIAL HOSPITAL SANAWAD+madhyapradesh&rlz=1C1CHBF_enIN859IN859&oq=LATE+SHRI NATTULALJI MORI MEMORIAL HOSPITAL SANAWAD+madhyapradesh&aqs=chrome..69i57j46i10i175i199j0i10l7.11711j0j15&sourceid=chrome&ie=UTF-8"
  },
  {
    "state": "Madhyapradesh",
    "hospitalName": "GURJAR SHRI HOSPITAL SANAWAD",
    "hospitalAdress": "Not Available",
    "district": "khargone",
    "phoneNo": "9685820097",
    "oxygenBedTotal": "-",
    "oxygenBedOccupied": "-",
    "oxygenBedAvailable": "13",
    "normalBedTotal": "-",
    "normalBedOccupied": "-",
    "normalBedAvailable": "-",
    "lastUpdatedDate": "25-05-2021",
    "lastUpdatedTime": " 18:09:59",
    "googleSearch": "https://www.google.com/search?q=GURJAR+SHRI HOSPITAL SANAWAD+madhyapradesh&rlz=1C1CHBF_enIN859IN859&oq=GURJAR+SHRI HOSPITAL SANAWAD+madhyapradesh&aqs=chrome..69i57j46i10i175i199j0i10l7.11711j0j15&sourceid=chrome&ie=UTF-8"
  },
  {
    "state": "Madhyapradesh",
    "hospitalName": "SONAA MAA NURSING HOME KHARGONE",
    "hospitalAdress": "Not Available",
    "district": "khargone",
    "phoneNo": "9407494894",
    "oxygenBedTotal": "-",
    "oxygenBedOccupied": "-",
    "oxygenBedAvailable": "20",
    "normalBedTotal": "-",
    "normalBedOccupied": "-",
    "normalBedAvailable": "-",
    "lastUpdatedDate": "25-05-2021",
    "lastUpdatedTime": " 18:05:35",
    "googleSearch": "https://www.google.com/search?q=SONAA+MAA NURSING HOME KHARGONE+madhyapradesh&rlz=1C1CHBF_enIN859IN859&oq=SONAA+MAA NURSING HOME KHARGONE+madhyapradesh&aqs=chrome..69i57j46i10i175i199j0i10l7.11711j0j15&sourceid=chrome&ie=UTF-8"
  },
  {
    "state": "Madhyapradesh",
    "hospitalName": "DH - KHARGONE",
    "hospitalAdress": "Not Available",
    "district": "khargone",
    "phoneNo": "8770748306",
    "oxygenBedTotal": "-",
    "oxygenBedOccupied": "-",
    "oxygenBedAvailable": "33",
    "normalBedTotal": "-",
    "normalBedOccupied": "-",
    "normalBedAvailable": "-",
    "lastUpdatedDate": "25-05-2021",
    "lastUpdatedTime": " 18:01:17",
    "googleSearch": "https://www.google.com/search?q=DH+- KHARGONE+madhyapradesh&rlz=1C1CHBF_enIN859IN859&oq=DH+- KHARGONE+madhyapradesh&aqs=chrome..69i57j46i10i175i199j0i10l7.11711j0j15&sourceid=chrome&ie=UTF-8"
  },
  {
    "state": "Madhyapradesh",
    "hospitalName": "SAI SAMARTH HOSPITAL KHARGONE",
    "hospitalAdress": "Not Available",
    "district": "khargone",
    "phoneNo": "9926892821",
    "oxygenBedTotal": "-",
    "oxygenBedOccupied": "-",
    "oxygenBedAvailable": "7",
    "normalBedTotal": "-",
    "normalBedOccupied": "-",
    "normalBedAvailable": "-",
    "lastUpdatedDate": "25-05-2021",
    "lastUpdatedTime": " 20:17:13",
    "googleSearch": "https://www.google.com/search?q=SAI+SAMARTH HOSPITAL KHARGONE+madhyapradesh&rlz=1C1CHBF_enIN859IN859&oq=SAI+SAMARTH HOSPITAL KHARGONE+madhyapradesh&aqs=chrome..69i57j46i10i175i199j0i10l7.11711j0j15&sourceid=chrome&ie=UTF-8"
  },
  {
    "state": "Madhyapradesh",
    "hospitalName": "CCC UMARKHALI ROAD KHARGONE",
    "hospitalAdress": "Not Available",
    "district": "khargone",
    "phoneNo": "8458986245",
    "oxygenBedTotal": "-",
    "oxygenBedOccupied": "-",
    "oxygenBedAvailable": "18",
    "normalBedTotal": "-",
    "normalBedOccupied": "-",
    "normalBedAvailable": "-",
    "lastUpdatedDate": "25-05-2021",
    "lastUpdatedTime": " 18:58:47",
    "googleSearch": "https://www.google.com/search?q=CCC+UMARKHALI ROAD KHARGONE+madhyapradesh&rlz=1C1CHBF_enIN859IN859&oq=CCC+UMARKHALI ROAD KHARGONE+madhyapradesh&aqs=chrome..69i57j46i10i175i199j0i10l7.11711j0j15&sourceid=chrome&ie=UTF-8"
  },
  {
    "state": "Madhyapradesh",
    "hospitalName": "SHRI DADA DARBAR HOSPITAL BARWAH",
    "hospitalAdress": "Not Available",
    "district": "khargone",
    "phoneNo": "7999756922",
    "oxygenBedTotal": "-",
    "oxygenBedOccupied": "-",
    "oxygenBedAvailable": "12",
    "normalBedTotal": "-",
    "normalBedOccupied": "-",
    "normalBedAvailable": "-",
    "lastUpdatedDate": "25-05-2021",
    "lastUpdatedTime": " 19:03:40",
    "googleSearch": "https://www.google.com/search?q=SHRI+DADA DARBAR HOSPITAL BARWAH+madhyapradesh&rlz=1C1CHBF_enIN859IN859&oq=SHRI+DADA DARBAR HOSPITAL BARWAH+madhyapradesh&aqs=chrome..69i57j46i10i175i199j0i10l7.11711j0j15&sourceid=chrome&ie=UTF-8"
  },
  {
    "state": "Madhyapradesh",
    "hospitalName": "NAVJEEVAN HOSPITAL KASRAWAD",
    "hospitalAdress": "Not Available",
    "district": "khargone",
    "phoneNo": "8208301224",
    "oxygenBedTotal": "-",
    "oxygenBedOccupied": "-",
    "oxygenBedAvailable": "16",
    "normalBedTotal": "-",
    "normalBedOccupied": "-",
    "normalBedAvailable": "-",
    "lastUpdatedDate": "25-05-2021",
    "lastUpdatedTime": " 20:25:37",
    "googleSearch": "https://www.google.com/search?q=NAVJEEVAN+HOSPITAL KASRAWAD+madhyapradesh&rlz=1C1CHBF_enIN859IN859&oq=NAVJEEVAN+HOSPITAL KASRAWAD+madhyapradesh&aqs=chrome..69i57j46i10i175i199j0i10l7.11711j0j15&sourceid=chrome&ie=UTF-8"
  },
  {
    "state": "Madhyapradesh",
    "hospitalName": "SUBHISHI HOSPITAL KHARGONE",
    "hospitalAdress": "Not Available",
    "district": "khargone",
    "phoneNo": "9039837881",
    "oxygenBedTotal": "-",
    "oxygenBedOccupied": "-",
    "oxygenBedAvailable": "14",
    "normalBedTotal": "-",
    "normalBedOccupied": "-",
    "normalBedAvailable": "-",
    "lastUpdatedDate": "25-05-2021",
    "lastUpdatedTime": " 18:51:08",
    "googleSearch": "https://www.google.com/search?q=SUBHISHI+HOSPITAL KHARGONE+madhyapradesh&rlz=1C1CHBF_enIN859IN859&oq=SUBHISHI+HOSPITAL KHARGONE+madhyapradesh&aqs=chrome..69i57j46i10i175i199j0i10l7.11711j0j15&sourceid=chrome&ie=UTF-8"
  },
  {
    "state": "Madhyapradesh",
    "hospitalName": "RITWIK HOSPITAL & RESEARCH CENTRE SANAWAD",
    "hospitalAdress": "Not Available",
    "district": "khargone",
    "phoneNo": "7049905639",
    "oxygenBedTotal": "-",
    "oxygenBedOccupied": "-",
    "oxygenBedAvailable": "1",
    "normalBedTotal": "-",
    "normalBedOccupied": "-",
    "normalBedAvailable": "-",
    "lastUpdatedDate": "25-05-2021",
    "lastUpdatedTime": " 18:15:06",
    "googleSearch": "https://www.google.com/search?q=RITWIK+HOSPITAL & RESEARCH CENTRE SANAWAD+madhyapradesh&rlz=1C1CHBF_enIN859IN859&oq=RITWIK+HOSPITAL & RESEARCH CENTRE SANAWAD+madhyapradesh&aqs=chrome..69i57j46i10i175i199j0i10l7.11711j0j15&sourceid=chrome&ie=UTF-8"
  },
  {
    "state": "Madhyapradesh",
    "hospitalName": "SHRI SAI HOSPITAL SANAWAD",
    "hospitalAdress": "Not Available",
    "district": "khargone",
    "phoneNo": "9826856222",
    "oxygenBedTotal": "-",
    "oxygenBedOccupied": "-",
    "oxygenBedAvailable": "15",
    "normalBedTotal": "-",
    "normalBedOccupied": "-",
    "normalBedAvailable": "-",
    "lastUpdatedDate": "25-05-2021",
    "lastUpdatedTime": " 20:06:20",
    "googleSearch": "https://www.google.com/search?q=SHRI+SAI HOSPITAL SANAWAD+madhyapradesh&rlz=1C1CHBF_enIN859IN859&oq=SHRI+SAI HOSPITAL SANAWAD+madhyapradesh&aqs=chrome..69i57j46i10i175i199j0i10l7.11711j0j15&sourceid=chrome&ie=UTF-8"
  },
  {
    "state": "Madhyapradesh",
    "hospitalName": "CCC KASRAWAD",
    "hospitalAdress": "Not Available",
    "district": "khargone",
    "phoneNo": "8319193500",
    "oxygenBedTotal": "-",
    "oxygenBedOccupied": "-",
    "oxygenBedAvailable": "15",
    "normalBedTotal": "-",
    "normalBedOccupied": "-",
    "normalBedAvailable": "-",
    "lastUpdatedDate": "25-05-2021",
    "lastUpdatedTime": " 20:41:10",
    "googleSearch": "https://www.google.com/search?q=CCC+KASRAWAD+madhyapradesh&rlz=1C1CHBF_enIN859IN859&oq=CCC+KASRAWAD+madhyapradesh&aqs=chrome..69i57j46i10i175i199j0i10l7.11711j0j15&sourceid=chrome&ie=UTF-8"
  },
  {
    "state": "Madhyapradesh",
    "hospitalName": "CCC SANAWAD",
    "hospitalAdress": "Not Available",
    "district": "khargone",
    "phoneNo": "9111470601",
    "oxygenBedTotal": "-",
    "oxygenBedOccupied": "-",
    "oxygenBedAvailable": "14",
    "normalBedTotal": "-",
    "normalBedOccupied": "-",
    "normalBedAvailable": "-",
    "lastUpdatedDate": "25-05-2021",
    "lastUpdatedTime": " 19:58:24",
    "googleSearch": "https://www.google.com/search?q=CCC+SANAWAD+madhyapradesh&rlz=1C1CHBF_enIN859IN859&oq=CCC+SANAWAD+madhyapradesh&aqs=chrome..69i57j46i10i175i199j0i10l7.11711j0j15&sourceid=chrome&ie=UTF-8"
  },
  {
    "state": "Madhyapradesh",
    "hospitalName": "CCC MAHESHWAR",
    "hospitalAdress": "Not Available",
    "district": "khargone",
    "phoneNo": "7067348179",
    "oxygenBedTotal": "-",
    "oxygenBedOccupied": "-",
    "oxygenBedAvailable": "15",
    "normalBedTotal": "-",
    "normalBedOccupied": "-",
    "normalBedAvailable": "-",
    "lastUpdatedDate": "25-05-2021",
    "lastUpdatedTime": " 19:17:28",
    "googleSearch": "https://www.google.com/search?q=CCC+MAHESHWAR+madhyapradesh&rlz=1C1CHBF_enIN859IN859&oq=CCC+MAHESHWAR+madhyapradesh&aqs=chrome..69i57j46i10i175i199j0i10l7.11711j0j15&sourceid=chrome&ie=UTF-8"
  },
  {
    "state": "Madhyapradesh",
    "hospitalName": "CCC BHIKANGAON",
    "hospitalAdress": "Not Available",
    "district": "khargone",
    "phoneNo": "7999623689",
    "oxygenBedTotal": "-",
    "oxygenBedOccupied": "-",
    "oxygenBedAvailable": "18",
    "normalBedTotal": "-",
    "normalBedOccupied": "-",
    "normalBedAvailable": "-",
    "lastUpdatedDate": "25-05-2021",
    "lastUpdatedTime": " 18:02:54",
    "googleSearch": "https://www.google.com/search?q=CCC+BHIKANGAON+madhyapradesh&rlz=1C1CHBF_enIN859IN859&oq=CCC+BHIKANGAON+madhyapradesh&aqs=chrome..69i57j46i10i175i199j0i10l7.11711j0j15&sourceid=chrome&ie=UTF-8"
  },
  {
    "state": "Madhyapradesh",
    "hospitalName": "GURJAR HOSPITAL BARWAH",
    "hospitalAdress": "Not Available",
    "district": "khargone",
    "phoneNo": "9826482217",
    "oxygenBedTotal": "-",
    "oxygenBedOccupied": "-",
    "oxygenBedAvailable": "1",
    "normalBedTotal": "-",
    "normalBedOccupied": "-",
    "normalBedAvailable": "-",
    "lastUpdatedDate": "25-05-2021",
    "lastUpdatedTime": " 20:17:27",
    "googleSearch": "https://www.google.com/search?q=GURJAR+HOSPITAL BARWAH+madhyapradesh&rlz=1C1CHBF_enIN859IN859&oq=GURJAR+HOSPITAL BARWAH+madhyapradesh&aqs=chrome..69i57j46i10i175i199j0i10l7.11711j0j15&sourceid=chrome&ie=UTF-8"
  },
  {
    "state": "Madhyapradesh",
    "hospitalName": "CCC RADHA KUNJ",
    "hospitalAdress": "Not Available",
    "district": "khargone",
    "phoneNo": "8720062846",
    "oxygenBedTotal": "-",
    "oxygenBedOccupied": "-",
    "oxygenBedAvailable": "20",
    "normalBedTotal": "-",
    "normalBedOccupied": "-",
    "normalBedAvailable": "-",
    "lastUpdatedDate": "25-05-2021",
    "lastUpdatedTime": " 19:54:33",
    "googleSearch": "https://www.google.com/search?q=CCC+RADHA KUNJ+madhyapradesh&rlz=1C1CHBF_enIN859IN859&oq=CCC+RADHA KUNJ+madhyapradesh&aqs=chrome..69i57j46i10i175i199j0i10l7.11711j0j15&sourceid=chrome&ie=UTF-8"
  },
  {
    "state": "Madhyapradesh",
    "hospitalName": "RAMSHREE HOSPITAL KHARGONE",
    "hospitalAdress": "Not Available",
    "district": "khargone",
    "phoneNo": "9009827410",
    "oxygenBedTotal": "-",
    "oxygenBedOccupied": "-",
    "oxygenBedAvailable": "15",
    "normalBedTotal": "-",
    "normalBedOccupied": "-",
    "normalBedAvailable": "-",
    "lastUpdatedDate": "25-05-2021",
    "lastUpdatedTime": " 19:12:37",
    "googleSearch": "https://www.google.com/search?q=RAMSHREE+HOSPITAL KHARGONE+madhyapradesh&rlz=1C1CHBF_enIN859IN859&oq=RAMSHREE+HOSPITAL KHARGONE+madhyapradesh&aqs=chrome..69i57j46i10i175i199j0i10l7.11711j0j15&sourceid=chrome&ie=UTF-8"
  },
  {
    "state": "Madhyapradesh",
    "hospitalName": "CCC BHAGWANPURA",
    "hospitalAdress": "Not Available",
    "district": "khargone",
    "phoneNo": "8959284698",
    "oxygenBedTotal": "-",
    "oxygenBedOccupied": "-",
    "oxygenBedAvailable": "20",
    "normalBedTotal": "-",
    "normalBedOccupied": "-",
    "normalBedAvailable": "-",
    "lastUpdatedDate": "25-05-2021",
    "lastUpdatedTime": " 18:02:36",
    "googleSearch": "https://www.google.com/search?q=CCC+BHAGWANPURA+madhyapradesh&rlz=1C1CHBF_enIN859IN859&oq=CCC+BHAGWANPURA+madhyapradesh&aqs=chrome..69i57j46i10i175i199j0i10l7.11711j0j15&sourceid=chrome&ie=UTF-8"
  },
  {
    "state": "Madhyapradesh",
    "hospitalName": "SHRI VISHNU SHRI HOSPITAL MAHESHWAR",
    "hospitalAdress": "Not Available",
    "district": "khargone",
    "phoneNo": "9074771966",
    "oxygenBedTotal": "-",
    "oxygenBedOccupied": "-",
    "oxygenBedAvailable": "5",
    "normalBedTotal": "-",
    "normalBedOccupied": "-",
    "normalBedAvailable": "-",
    "lastUpdatedDate": "25-05-2021",
    "lastUpdatedTime": " 19:24:56",
    "googleSearch": "https://www.google.com/search?q=SHRI+VISHNU SHRI HOSPITAL MAHESHWAR+madhyapradesh&rlz=1C1CHBF_enIN859IN859&oq=SHRI+VISHNU SHRI HOSPITAL MAHESHWAR+madhyapradesh&aqs=chrome..69i57j46i10i175i199j0i10l7.11711j0j15&sourceid=chrome&ie=UTF-8"
  },
  {
    "state": "Madhyapradesh",
    "hospitalName": "RUDRANSH HOSPITAL & CRITICAL CARE BHIKANGAON",
    "hospitalAdress": "Not Available",
    "district": "khargone",
    "phoneNo": "7974860412",
    "oxygenBedTotal": "-",
    "oxygenBedOccupied": "-",
    "oxygenBedAvailable": "3",
    "normalBedTotal": "-",
    "normalBedOccupied": "-",
    "normalBedAvailable": "-",
    "lastUpdatedDate": "25-05-2021",
    "lastUpdatedTime": " 19:58:25",
    "googleSearch": "https://www.google.com/search?q=RUDRANSH+HOSPITAL & CRITICAL CARE BHIKANGAON+madhyapradesh&rlz=1C1CHBF_enIN859IN859&oq=RUDRANSH+HOSPITAL & CRITICAL CARE BHIKANGAON+madhyapradesh&aqs=chrome..69i57j46i10i175i199j0i10l7.11711j0j15&sourceid=chrome&ie=UTF-8"
  },
  {
    "state": "Madhyapradesh",
    "hospitalName": "AGRAWAL HOSPITAL SANAWAD",
    "hospitalAdress": "Not Available",
    "district": "khargone",
    "phoneNo": "9926958001",
    "oxygenBedTotal": "-",
    "oxygenBedOccupied": "-",
    "oxygenBedAvailable": "5",
    "normalBedTotal": "-",
    "normalBedOccupied": "-",
    "normalBedAvailable": "-",
    "lastUpdatedDate": "25-05-2021",
    "lastUpdatedTime": " 18:50:16",
    "googleSearch": "https://www.google.com/search?q=AGRAWAL+HOSPITAL SANAWAD+madhyapradesh&rlz=1C1CHBF_enIN859IN859&oq=AGRAWAL+HOSPITAL SANAWAD+madhyapradesh&aqs=chrome..69i57j46i10i175i199j0i10l7.11711j0j15&sourceid=chrome&ie=UTF-8"
  },
  {
    "state": "Madhyapradesh",
    "hospitalName": "CCC SARASVATI SCHOOL KGN",
    "hospitalAdress": "Not Available",
    "district": "khargone",
    "phoneNo": "9165673789",
    "oxygenBedTotal": "-",
    "oxygenBedOccupied": "-",
    "oxygenBedAvailable": "20",
    "normalBedTotal": "-",
    "normalBedOccupied": "-",
    "normalBedAvailable": "-",
    "lastUpdatedDate": "25-05-2021",
    "lastUpdatedTime": " 18:07:09",
    "googleSearch": "https://www.google.com/search?q=CCC+SARASVATI SCHOOL KGN+madhyapradesh&rlz=1C1CHBF_enIN859IN859&oq=CCC+SARASVATI SCHOOL KGN+madhyapradesh&aqs=chrome..69i57j46i10i175i199j0i10l7.11711j0j15&sourceid=chrome&ie=UTF-8"
  },
  {
    "state": "Madhyapradesh",
    "hospitalName": "SUJAS HOSPITAL MANDLESHWAR",
    "hospitalAdress": "Not Available",
    "district": "khargone",
    "phoneNo": "9827722252",
    "oxygenBedTotal": "-",
    "oxygenBedOccupied": "-",
    "oxygenBedAvailable": "32",
    "normalBedTotal": "-",
    "normalBedOccupied": "-",
    "normalBedAvailable": "-",
    "lastUpdatedDate": "25-05-2021",
    "lastUpdatedTime": " 18:33:23",
    "googleSearch": "https://www.google.com/search?q=SUJAS+HOSPITAL MANDLESHWAR+madhyapradesh&rlz=1C1CHBF_enIN859IN859&oq=SUJAS+HOSPITAL MANDLESHWAR+madhyapradesh&aqs=chrome..69i57j46i10i175i199j0i10l7.11711j0j15&sourceid=chrome&ie=UTF-8"
  },
  {
    "state": "Madhyapradesh",
    "hospitalName": "CCC  OON",
    "hospitalAdress": "Not Available",
    "district": "khargone",
    "phoneNo": "7987002635",
    "oxygenBedTotal": "-",
    "oxygenBedOccupied": "-",
    "oxygenBedAvailable": "20",
    "normalBedTotal": "-",
    "normalBedOccupied": "-",
    "normalBedAvailable": "-",
    "lastUpdatedDate": "25-05-2021",
    "lastUpdatedTime": " 18:51:39",
    "googleSearch": "https://www.google.com/search?q=CCC+ OON+madhyapradesh&rlz=1C1CHBF_enIN859IN859&oq=CCC+ OON+madhyapradesh&aqs=chrome..69i57j46i10i175i199j0i10l7.11711j0j15&sourceid=chrome&ie=UTF-8"
  },
  {
    "state": "Madhyapradesh",
    "hospitalName": "CCC GOGAWA",
    "hospitalAdress": "Not Available",
    "district": "khargone",
    "phoneNo": "9009451900",
    "oxygenBedTotal": "-",
    "oxygenBedOccupied": "-",
    "oxygenBedAvailable": "20",
    "normalBedTotal": "-",
    "normalBedOccupied": "-",
    "normalBedAvailable": "-",
    "lastUpdatedDate": "25-05-2021",
    "lastUpdatedTime": " 20:04:54",
    "googleSearch": "https://www.google.com/search?q=CCC+GOGAWA+madhyapradesh&rlz=1C1CHBF_enIN859IN859&oq=CCC+GOGAWA+madhyapradesh&aqs=chrome..69i57j46i10i175i199j0i10l7.11711j0j15&sourceid=chrome&ie=UTF-8"
  },
  {
    "state": "Madhyapradesh",
    "hospitalName": "CCC BARWAH",
    "hospitalAdress": "Not Available",
    "district": "khargone",
    "phoneNo": "9406502607",
    "oxygenBedTotal": "-",
    "oxygenBedOccupied": "-",
    "oxygenBedAvailable": "19",
    "normalBedTotal": "-",
    "normalBedOccupied": "-",
    "normalBedAvailable": "-",
    "lastUpdatedDate": "25-05-2021",
    "lastUpdatedTime": " 18:12:12",
    "googleSearch": "https://www.google.com/search?q=CCC+BARWAH+madhyapradesh&rlz=1C1CHBF_enIN859IN859&oq=CCC+BARWAH+madhyapradesh&aqs=chrome..69i57j46i10i175i199j0i10l7.11711j0j15&sourceid=chrome&ie=UTF-8"
  },
  {
    "state": "Madhyapradesh",
    "hospitalName": "CCC SEGAON",
    "hospitalAdress": "Not Available",
    "district": "khargone",
    "phoneNo": "7089944815",
    "oxygenBedTotal": "-",
    "oxygenBedOccupied": "-",
    "oxygenBedAvailable": "20",
    "normalBedTotal": "-",
    "normalBedOccupied": "-",
    "normalBedAvailable": "-",
    "lastUpdatedDate": "25-05-2021",
    "lastUpdatedTime": " 19:53:47",
    "googleSearch": "https://www.google.com/search?q=CCC+SEGAON+madhyapradesh&rlz=1C1CHBF_enIN859IN859&oq=CCC+SEGAON+madhyapradesh&aqs=chrome..69i57j46i10i175i199j0i10l7.11711j0j15&sourceid=chrome&ie=UTF-8"
  }
]