[
  {
    "hospitalName": "LATE SHRI NATTULALJI MORI MEMORIAL HOSPITAL SANAWAD",
    "hospitalAddress": "Not Available",
    "normalBedTotal": "24 ",
    "normalBedOccupied": "-",
    "normalBedAvailable": "0",
    "oxygenBedTotal": "-",
    "oxygenBedOccupied": "-",
    "oxygenBedAvailable": "0",
    "lastUpdatedDate": "21-05-2021",
    "lastUpdatedTime": "19:17:21",
    "district": "",
    "state": "Madhyapradesh",
    "googleSearch": "https://www.google.com/search?q=LATE+SHRI NATTULALJI MORI MEMORIAL HOSPITAL SANAWAD+Madhya+Pradesh&rlz=1C1CHBF_enIN859IN859&oq=LATE+SHRI NATTULALJI MORI MEMORIAL HOSPITAL SANAWAD+Madhya+Pradesh&aqs=chrome..69i57j46i10i175i199j0i10l7.11711j0j15&sourceid=chrome&ie=UTF-8",
    "phoneNo": "Not Available"
  },
  {
    "hospitalName": "GURJAR SHRI HOSPITAL SANAWAD",
    "hospitalAddress": "Not Available",
    "normalBedTotal": "53 ",
    "normalBedOccupied": "-",
    "normalBedAvailable": "48",
    "oxygenBedTotal": "-",
    "oxygenBedOccupied": "-",
    "oxygenBedAvailable": "13",
    "lastUpdatedDate": "21-05-2021",
    "lastUpdatedTime": "18:55:04",
    "district": "",
    "state": "Madhyapradesh",
    "googleSearch": "https://www.google.com/search?q=GURJAR+SHRI HOSPITAL SANAWAD+Madhya+Pradesh&rlz=1C1CHBF_enIN859IN859&oq=GURJAR+SHRI HOSPITAL SANAWAD+Madhya+Pradesh&aqs=chrome..69i57j46i10i175i199j0i10l7.11711j0j15&sourceid=chrome&ie=UTF-8",
    "phoneNo": "Not Available"
  },
  {
    "hospitalName": "SONAA MAA NURSING HOME KHARGONE",
    "hospitalAddress": "Not Available",
    "normalBedTotal": "20 ",
    "normalBedOccupied": "-",
    "normalBedAvailable": "16",
    "oxygenBedTotal": "-",
    "oxygenBedOccupied": "-",
    "oxygenBedAvailable": "16",
    "lastUpdatedDate": "21-05-2021",
    "lastUpdatedTime": "18:17:04",
    "district": "",
    "state": "Madhyapradesh",
    "googleSearch": "https://www.google.com/search?q=SONAA+MAA NURSING HOME KHARGONE+Madhya+Pradesh&rlz=1C1CHBF_enIN859IN859&oq=SONAA+MAA NURSING HOME KHARGONE+Madhya+Pradesh&aqs=chrome..69i57j46i10i175i199j0i10l7.11711j0j15&sourceid=chrome&ie=UTF-8",
    "phoneNo": "Not Available"
  },
  {
    "hospitalName": "DH - KHARGONE",
    "hospitalAddress": "Not Available",
    "normalBedTotal": "208 ",
    "normalBedOccupied": "-",
    "normalBedAvailable": "89",
    "oxygenBedTotal": "-",
    "oxygenBedOccupied": "-",
    "oxygenBedAvailable": "13",
    "lastUpdatedDate": "21-05-2021",
    "lastUpdatedTime": "18:30:12",
    "district": "",
    "state": "Madhyapradesh",
    "googleSearch": "https://www.google.com/search?q=DH+- KHARGONE+Madhya+Pradesh&rlz=1C1CHBF_enIN859IN859&oq=DH+- KHARGONE+Madhya+Pradesh&aqs=chrome..69i57j46i10i175i199j0i10l7.11711j0j15&sourceid=chrome&ie=UTF-8",
    "phoneNo": "Not Available"
  },
  {
    "hospitalName": "SAI SAMARTH HOSPITAL KHARGONE",
    "hospitalAddress": "Not Available",
    "normalBedTotal": "40 ",
    "normalBedOccupied": "-",
    "normalBedAvailable": "17",
    "oxygenBedTotal": "-",
    "oxygenBedOccupied": "-",
    "oxygenBedAvailable": "6",
    "lastUpdatedDate": "21-05-2021",
    "lastUpdatedTime": "20:50:57",
    "district": "",
    "state": "Madhyapradesh",
    "googleSearch": "https://www.google.com/search?q=SAI+SAMARTH HOSPITAL KHARGONE+Madhya+Pradesh&rlz=1C1CHBF_enIN859IN859&oq=SAI+SAMARTH HOSPITAL KHARGONE+Madhya+Pradesh&aqs=chrome..69i57j46i10i175i199j0i10l7.11711j0j15&sourceid=chrome&ie=UTF-8",
    "phoneNo": "Not Available"
  },
  {
    "hospitalName": "CCC UMARKHALI ROAD KHARGONE",
    "hospitalAddress": "Not Available",
    "normalBedTotal": "110 ",
    "normalBedOccupied": "-",
    "normalBedAvailable": "70",
    "oxygenBedTotal": "-",
    "oxygenBedOccupied": "-",
    "oxygenBedAvailable": "16",
    "lastUpdatedDate": "21-05-2021",
    "lastUpdatedTime": "19:07:51",
    "district": "",
    "state": "Madhyapradesh",
    "googleSearch": "https://www.google.com/search?q=CCC+UMARKHALI ROAD KHARGONE+Madhya+Pradesh&rlz=1C1CHBF_enIN859IN859&oq=CCC+UMARKHALI ROAD KHARGONE+Madhya+Pradesh&aqs=chrome..69i57j46i10i175i199j0i10l7.11711j0j15&sourceid=chrome&ie=UTF-8",
    "phoneNo": "Not Available"
  },
  {
    "hospitalName": "SHRI DADA DARBAR HOSPITAL BARWAH",
    "hospitalAddress": "Not Available",
    "normalBedTotal": "30 ",
    "normalBedOccupied": "-",
    "normalBedAvailable": "28",
    "oxygenBedTotal": "-",
    "oxygenBedOccupied": "-",
    "oxygenBedAvailable": "13",
    "lastUpdatedDate": "21-05-2021",
    "lastUpdatedTime": "19:57:24",
    "district": "",
    "state": "Madhyapradesh",
    "googleSearch": "https://www.google.com/search?q=SHRI+DADA DARBAR HOSPITAL BARWAH+Madhya+Pradesh&rlz=1C1CHBF_enIN859IN859&oq=SHRI+DADA DARBAR HOSPITAL BARWAH+Madhya+Pradesh&aqs=chrome..69i57j46i10i175i199j0i10l7.11711j0j15&sourceid=chrome&ie=UTF-8",
    "phoneNo": "Not Available"
  },
  {
    "hospitalName": "NAVJEEVAN HOSPITAL KASRAWAD",
    "hospitalAddress": "Not Available",
    "normalBedTotal": "32 ",
    "normalBedOccupied": "-",
    "normalBedAvailable": "24",
    "oxygenBedTotal": "-",
    "oxygenBedOccupied": "-",
    "oxygenBedAvailable": "13",
    "lastUpdatedDate": "21-05-2021",
    "lastUpdatedTime": "20:36:18",
    "district": "",
    "state": "Madhyapradesh",
    "googleSearch": "https://www.google.com/search?q=NAVJEEVAN+HOSPITAL KASRAWAD+Madhya+Pradesh&rlz=1C1CHBF_enIN859IN859&oq=NAVJEEVAN+HOSPITAL KASRAWAD+Madhya+Pradesh&aqs=chrome..69i57j46i10i175i199j0i10l7.11711j0j15&sourceid=chrome&ie=UTF-8",
    "phoneNo": "Not Available"
  },
  {
    "hospitalName": "SUBHISHI HOSPITAL KHARGONE",
    "hospitalAddress": "Not Available",
    "normalBedTotal": "52 ",
    "normalBedOccupied": "-",
    "normalBedAvailable": "35",
    "oxygenBedTotal": "-",
    "oxygenBedOccupied": "-",
    "oxygenBedAvailable": "21",
    "lastUpdatedDate": "21-05-2021",
    "lastUpdatedTime": "20:58:04",
    "district": "",
    "state": "Madhyapradesh",
    "googleSearch": "https://www.google.com/search?q=SUBHISHI+HOSPITAL KHARGONE+Madhya+Pradesh&rlz=1C1CHBF_enIN859IN859&oq=SUBHISHI+HOSPITAL KHARGONE+Madhya+Pradesh&aqs=chrome..69i57j46i10i175i199j0i10l7.11711j0j15&sourceid=chrome&ie=UTF-8",
    "phoneNo": "Not Available"
  },
  {
    "hospitalName": "RITWIK HOSPITAL & RESEARCH CENTRE SANAWAD",
    "hospitalAddress": "Not Available",
    "normalBedTotal": "15 ",
    "normalBedOccupied": "-",
    "normalBedAvailable": "9",
    "oxygenBedTotal": "-",
    "oxygenBedOccupied": "-",
    "oxygenBedAvailable": "1",
    "lastUpdatedDate": "21-05-2021",
    "lastUpdatedTime": "18:16:06",
    "district": "",
    "state": "Madhyapradesh",
    "googleSearch": "https://www.google.com/search?q=RITWIK+HOSPITAL & RESEARCH CENTRE SANAWAD+Madhya+Pradesh&rlz=1C1CHBF_enIN859IN859&oq=RITWIK+HOSPITAL & RESEARCH CENTRE SANAWAD+Madhya+Pradesh&aqs=chrome..69i57j46i10i175i199j0i10l7.11711j0j15&sourceid=chrome&ie=UTF-8",
    "phoneNo": "Not Available"
  },
  {
    "hospitalName": "SHRI SAI HOSPITAL SANAWAD",
    "hospitalAddress": "Not Available",
    "normalBedTotal": "36 ",
    "normalBedOccupied": "-",
    "normalBedAvailable": "20",
    "oxygenBedTotal": "-",
    "oxygenBedOccupied": "-",
    "oxygenBedAvailable": "9",
    "lastUpdatedDate": "21-05-2021",
    "lastUpdatedTime": "20:11:41",
    "district": "",
    "state": "Madhyapradesh",
    "googleSearch": "https://www.google.com/search?q=SHRI+SAI HOSPITAL SANAWAD+Madhya+Pradesh&rlz=1C1CHBF_enIN859IN859&oq=SHRI+SAI HOSPITAL SANAWAD+Madhya+Pradesh&aqs=chrome..69i57j46i10i175i199j0i10l7.11711j0j15&sourceid=chrome&ie=UTF-8",
    "phoneNo": "Not Available"
  },
  {
    "hospitalName": "CCC KASRAWAD",
    "hospitalAddress": "Not Available",
    "normalBedTotal": "50 ",
    "normalBedOccupied": "-",
    "normalBedAvailable": "30",
    "oxygenBedTotal": "-",
    "oxygenBedOccupied": "-",
    "oxygenBedAvailable": "11",
    "lastUpdatedDate": "21-05-2021",
    "lastUpdatedTime": "20:58:37",
    "district": "",
    "state": "Madhyapradesh",
    "googleSearch": "https://www.google.com/search?q=CCC+KASRAWAD+Madhya+Pradesh&rlz=1C1CHBF_enIN859IN859&oq=CCC+KASRAWAD+Madhya+Pradesh&aqs=chrome..69i57j46i10i175i199j0i10l7.11711j0j15&sourceid=chrome&ie=UTF-8",
    "phoneNo": "Not Available"
  },
  {
    "hospitalName": "CCC SANAWAD",
    "hospitalAddress": "Not Available",
    "normalBedTotal": "60 ",
    "normalBedOccupied": "-",
    "normalBedAvailable": "49",
    "oxygenBedTotal": "-",
    "oxygenBedOccupied": "-",
    "oxygenBedAvailable": "12",
    "lastUpdatedDate": "21-05-2021",
    "lastUpdatedTime": "20:04:01",
    "district": "",
    "state": "Madhyapradesh",
    "googleSearch": "https://www.google.com/search?q=CCC+SANAWAD+Madhya+Pradesh&rlz=1C1CHBF_enIN859IN859&oq=CCC+SANAWAD+Madhya+Pradesh&aqs=chrome..69i57j46i10i175i199j0i10l7.11711j0j15&sourceid=chrome&ie=UTF-8",
    "phoneNo": "Not Available"
  },
  {
    "hospitalName": "CCC MAHESHWAR",
    "hospitalAddress": "Not Available",
    "normalBedTotal": "110 ",
    "normalBedOccupied": "-",
    "normalBedAvailable": "91",
    "oxygenBedTotal": "-",
    "oxygenBedOccupied": "-",
    "oxygenBedAvailable": "18",
    "lastUpdatedDate": "21-05-2021",
    "lastUpdatedTime": "18:19:44",
    "district": "",
    "state": "Madhyapradesh",
    "googleSearch": "https://www.google.com/search?q=CCC+MAHESHWAR+Madhya+Pradesh&rlz=1C1CHBF_enIN859IN859&oq=CCC+MAHESHWAR+Madhya+Pradesh&aqs=chrome..69i57j46i10i175i199j0i10l7.11711j0j15&sourceid=chrome&ie=UTF-8",
    "phoneNo": "Not Available"
  },
  {
    "hospitalName": "CCC BHIKANGAON",
    "hospitalAddress": "Not Available",
    "normalBedTotal": "70 ",
    "normalBedOccupied": "-",
    "normalBedAvailable": "62",
    "oxygenBedTotal": "-",
    "oxygenBedOccupied": "-",
    "oxygenBedAvailable": "18",
    "lastUpdatedDate": "21-05-2021",
    "lastUpdatedTime": "18:41:47",
    "district": "",
    "state": "Madhyapradesh",
    "googleSearch": "https://www.google.com/search?q=CCC+BHIKANGAON+Madhya+Pradesh&rlz=1C1CHBF_enIN859IN859&oq=CCC+BHIKANGAON+Madhya+Pradesh&aqs=chrome..69i57j46i10i175i199j0i10l7.11711j0j15&sourceid=chrome&ie=UTF-8",
    "phoneNo": "Not Available"
  },
  {
    "hospitalName": "GURJAR HOSPITAL BARWAH",
    "hospitalAddress": "Not Available",
    "normalBedTotal": "24 ",
    "normalBedOccupied": "-",
    "normalBedAvailable": "20",
    "oxygenBedTotal": "-",
    "oxygenBedOccupied": "-",
    "oxygenBedAvailable": "8",
    "lastUpdatedDate": "21-05-2021",
    "lastUpdatedTime": "19:40:01",
    "district": "",
    "state": "Madhyapradesh",
    "googleSearch": "https://www.google.com/search?q=GURJAR+HOSPITAL BARWAH+Madhya+Pradesh&rlz=1C1CHBF_enIN859IN859&oq=GURJAR+HOSPITAL BARWAH+Madhya+Pradesh&aqs=chrome..69i57j46i10i175i199j0i10l7.11711j0j15&sourceid=chrome&ie=UTF-8",
    "phoneNo": "Not Available"
  },
  {
    "hospitalName": "CCC RADHA KUNJ",
    "hospitalAddress": "Not Available",
    "normalBedTotal": "55 ",
    "normalBedOccupied": "-",
    "normalBedAvailable": "52",
    "oxygenBedTotal": "-",
    "oxygenBedOccupied": "-",
    "oxygenBedAvailable": "20",
    "lastUpdatedDate": "21-05-2021",
    "lastUpdatedTime": "21:05:25",
    "district": "",
    "state": "Madhyapradesh",
    "googleSearch": "https://www.google.com/search?q=CCC+RADHA KUNJ+Madhya+Pradesh&rlz=1C1CHBF_enIN859IN859&oq=CCC+RADHA KUNJ+Madhya+Pradesh&aqs=chrome..69i57j46i10i175i199j0i10l7.11711j0j15&sourceid=chrome&ie=UTF-8",
    "phoneNo": "Not Available"
  },
  {
    "hospitalName": "RAMSHREE HOSPITAL KHARGONE",
    "hospitalAddress": "Not Available",
    "normalBedTotal": "30 ",
    "normalBedOccupied": "-",
    "normalBedAvailable": "22",
    "oxygenBedTotal": "-",
    "oxygenBedOccupied": "-",
    "oxygenBedAvailable": "13",
    "lastUpdatedDate": "21-05-2021",
    "lastUpdatedTime": "18:52:06",
    "district": "",
    "state": "Madhyapradesh",
    "googleSearch": "https://www.google.com/search?q=RAMSHREE+HOSPITAL KHARGONE+Madhya+Pradesh&rlz=1C1CHBF_enIN859IN859&oq=RAMSHREE+HOSPITAL KHARGONE+Madhya+Pradesh&aqs=chrome..69i57j46i10i175i199j0i10l7.11711j0j15&sourceid=chrome&ie=UTF-8",
    "phoneNo": "Not Available"
  },
  {
    "hospitalName": "CCC BHAGWANPURA",
    "hospitalAddress": "Not Available",
    "normalBedTotal": "50 ",
    "normalBedOccupied": "-",
    "normalBedAvailable": "50",
    "oxygenBedTotal": "-",
    "oxygenBedOccupied": "-",
    "oxygenBedAvailable": "20",
    "lastUpdatedDate": "21-05-2021",
    "lastUpdatedTime": "18:29:49",
    "district": "",
    "state": "Madhyapradesh",
    "googleSearch": "https://www.google.com/search?q=CCC+BHAGWANPURA+Madhya+Pradesh&rlz=1C1CHBF_enIN859IN859&oq=CCC+BHAGWANPURA+Madhya+Pradesh&aqs=chrome..69i57j46i10i175i199j0i10l7.11711j0j15&sourceid=chrome&ie=UTF-8",
    "phoneNo": "Not Available"
  },
  {
    "hospitalName": "SHRI VISHNU SHRI HOSPITAL MAHESHWAR",
    "hospitalAddress": "Not Available",
    "normalBedTotal": "30 ",
    "normalBedOccupied": "-",
    "normalBedAvailable": "16",
    "oxygenBedTotal": "-",
    "oxygenBedOccupied": "-",
    "oxygenBedAvailable": "5",
    "lastUpdatedDate": "21-05-2021",
    "lastUpdatedTime": "21:00:36",
    "district": "",
    "state": "Madhyapradesh",
    "googleSearch": "https://www.google.com/search?q=SHRI+VISHNU SHRI HOSPITAL MAHESHWAR+Madhya+Pradesh&rlz=1C1CHBF_enIN859IN859&oq=SHRI+VISHNU SHRI HOSPITAL MAHESHWAR+Madhya+Pradesh&aqs=chrome..69i57j46i10i175i199j0i10l7.11711j0j15&sourceid=chrome&ie=UTF-8",
    "phoneNo": "Not Available"
  },
  {
    "hospitalName": "RUDRANSH HOSPITAL & CRITICAL CARE BHIKANGAON",
    "hospitalAddress": "Not Available",
    "normalBedTotal": "14 ",
    "normalBedOccupied": "-",
    "normalBedAvailable": "10",
    "oxygenBedTotal": "-",
    "oxygenBedOccupied": "-",
    "oxygenBedAvailable": "3",
    "lastUpdatedDate": "21-05-2021",
    "lastUpdatedTime": "20:52:12",
    "district": "",
    "state": "Madhyapradesh",
    "googleSearch": "https://www.google.com/search?q=RUDRANSH+HOSPITAL & CRITICAL CARE BHIKANGAON+Madhya+Pradesh&rlz=1C1CHBF_enIN859IN859&oq=RUDRANSH+HOSPITAL & CRITICAL CARE BHIKANGAON+Madhya+Pradesh&aqs=chrome..69i57j46i10i175i199j0i10l7.11711j0j15&sourceid=chrome&ie=UTF-8",
    "phoneNo": "Not Available"
  },
  {
    "hospitalName": "AGRAWAL HOSPITAL SANAWAD",
    "hospitalAddress": "Not Available",
    "normalBedTotal": "20 ",
    "normalBedOccupied": "-",
    "normalBedAvailable": "1",
    "oxygenBedTotal": "-",
    "oxygenBedOccupied": "-",
    "oxygenBedAvailable": "0",
    "lastUpdatedDate": "21-05-2021",
    "lastUpdatedTime": "19:28:35",
    "district": "",
    "state": "Madhyapradesh",
    "googleSearch": "https://www.google.com/search?q=AGRAWAL+HOSPITAL SANAWAD+Madhya+Pradesh&rlz=1C1CHBF_enIN859IN859&oq=AGRAWAL+HOSPITAL SANAWAD+Madhya+Pradesh&aqs=chrome..69i57j46i10i175i199j0i10l7.11711j0j15&sourceid=chrome&ie=UTF-8",
    "phoneNo": "Not Available"
  },
  {
    "hospitalName": "CCC SARASVATI SCHOOL KGN",
    "hospitalAddress": "Not Available",
    "normalBedTotal": "65 ",
    "normalBedOccupied": "-",
    "normalBedAvailable": "65",
    "oxygenBedTotal": "-",
    "oxygenBedOccupied": "-",
    "oxygenBedAvailable": "20",
    "lastUpdatedDate": "21-05-2021",
    "lastUpdatedTime": "18:43:31",
    "district": "",
    "state": "Madhyapradesh",
    "googleSearch": "https://www.google.com/search?q=CCC+SARASVATI SCHOOL KGN+Madhya+Pradesh&rlz=1C1CHBF_enIN859IN859&oq=CCC+SARASVATI SCHOOL KGN+Madhya+Pradesh&aqs=chrome..69i57j46i10i175i199j0i10l7.11711j0j15&sourceid=chrome&ie=UTF-8",
    "phoneNo": "Not Available"
  },
  {
    "hospitalName": "SUJAS HOSPITAL MANDLESHWAR",
    "hospitalAddress": "Not Available",
    "normalBedTotal": "57 ",
    "normalBedOccupied": "-",
    "normalBedAvailable": "55",
    "oxygenBedTotal": "-",
    "oxygenBedOccupied": "-",
    "oxygenBedAvailable": "32",
    "lastUpdatedDate": "21-05-2021",
    "lastUpdatedTime": "20:20:37",
    "district": "",
    "state": "Madhyapradesh",
    "googleSearch": "https://www.google.com/search?q=SUJAS+HOSPITAL MANDLESHWAR+Madhya+Pradesh&rlz=1C1CHBF_enIN859IN859&oq=SUJAS+HOSPITAL MANDLESHWAR+Madhya+Pradesh&aqs=chrome..69i57j46i10i175i199j0i10l7.11711j0j15&sourceid=chrome&ie=UTF-8",
    "phoneNo": "Not Available"
  },
  {
    "hospitalName": "CCC OON",
    "hospitalAddress": "Not Available",
    "normalBedTotal": "50 ",
    "normalBedOccupied": "-",
    "normalBedAvailable": "46",
    "oxygenBedTotal": "-",
    "oxygenBedOccupied": "-",
    "oxygenBedAvailable": "20",
    "lastUpdatedDate": "21-05-2021",
    "lastUpdatedTime": "18:11:34",
    "district": "",
    "state": "Madhyapradesh",
    "googleSearch": "https://www.google.com/search?q=CCC+OON+Madhya+Pradesh&rlz=1C1CHBF_enIN859IN859&oq=CCC+OON+Madhya+Pradesh&aqs=chrome..69i57j46i10i175i199j0i10l7.11711j0j15&sourceid=chrome&ie=UTF-8",
    "phoneNo": "Not Available"
  },
  {
    "hospitalName": "CCC GOGAWA",
    "hospitalAddress": "Not Available",
    "normalBedTotal": "36 ",
    "normalBedOccupied": "-",
    "normalBedAvailable": "31",
    "oxygenBedTotal": "-",
    "oxygenBedOccupied": "-",
    "oxygenBedAvailable": "19",
    "lastUpdatedDate": "21-05-2021",
    "lastUpdatedTime": "09:55:02",
    "district": "",
    "state": "Madhyapradesh",
    "googleSearch": "https://www.google.com/search?q=CCC+GOGAWA+Madhya+Pradesh&rlz=1C1CHBF_enIN859IN859&oq=CCC+GOGAWA+Madhya+Pradesh&aqs=chrome..69i57j46i10i175i199j0i10l7.11711j0j15&sourceid=chrome&ie=UTF-8",
    "phoneNo": "Not Available"
  },
  {
    "hospitalName": "CCC BARWAH",
    "hospitalAddress": "Not Available",
    "normalBedTotal": "50 ",
    "normalBedOccupied": "-",
    "normalBedAvailable": "44",
    "oxygenBedTotal": "-",
    "oxygenBedOccupied": "-",
    "oxygenBedAvailable": "14",
    "lastUpdatedDate": "21-05-2021",
    "lastUpdatedTime": "18:51:47",
    "district": "",
    "state": "Madhyapradesh",
    "googleSearch": "https://www.google.com/search?q=CCC+BARWAH+Madhya+Pradesh&rlz=1C1CHBF_enIN859IN859&oq=CCC+BARWAH+Madhya+Pradesh&aqs=chrome..69i57j46i10i175i199j0i10l7.11711j0j15&sourceid=chrome&ie=UTF-8",
    "phoneNo": "Not Available"
  },
  {
    "hospitalName": "CCC SEGAON",
    "hospitalAddress": "Not Available",
    "normalBedTotal": "50 ",
    "normalBedOccupied": "-",
    "normalBedAvailable": "44",
    "oxygenBedTotal": "-",
    "oxygenBedOccupied": "-",
    "oxygenBedAvailable": "20",
    "lastUpdatedDate": "21-05-2021",
    "lastUpdatedTime": "19:11:54",
    "district": "",
    "state": "Madhyapradesh",
    "googleSearch": "https://www.google.com/search?q=CCC+SEGAON+Madhya+Pradesh&rlz=1C1CHBF_enIN859IN859&oq=CCC+SEGAON+Madhya+Pradesh&aqs=chrome..69i57j46i10i175i199j0i10l7.11711j0j15&sourceid=chrome&ie=UTF-8",
    "phoneNo": "Not Available"
  },
  {
    "hospitalName": "CCC KARHI",
    "hospitalAddress": "Not Available",
    "normalBedTotal": "55 ",
    "normalBedOccupied": "-",
    "normalBedAvailable": "55",
    "oxygenBedTotal": "-",
    "oxygenBedOccupied": "-",
    "oxygenBedAvailable": "20",
    "lastUpdatedDate": "21-05-2021",
    "lastUpdatedTime": "11:11:27",
    "district": "",
    "state": "Madhyapradesh",
    "googleSearch": "https://www.google.com/search?q=CCC+KARHI+Madhya+Pradesh&rlz=1C1CHBF_enIN859IN859&oq=CCC+KARHI+Madhya+Pradesh&aqs=chrome..69i57j46i10i175i199j0i10l7.11711j0j15&sourceid=chrome&ie=UTF-8",
    "phoneNo": "Not Available"
  }
]