[
  {
    "state": "Haryana",
    "district": "panchkula",
    "hospitalName": " Alchemist Hospital panchkula",
    "hospitalAdress": "Not Available",
    "phoneNo": "01724500000",
    "oxygenBedTotal": 43,
    "oxygenBedOccupied": " 42",
    "oxygenBedAvailable": "1",
    "normalBedTotal": null,
    "normalBedOccupied": " 0",
    "lastUpdatedDate": " 11:13 AM 26th May,21",
    "lastUpdatedTime": " 11:13 AM",
    "googleSearch": "https://www.google.com/search?q=+Alchemist Hospital panchkula+panchkula&rlz=1C1CHBF_enIN859IN859&oq=+Alchemist Hospital panchkula+panchkula&aqs=chrome..69i57j46i10i175i199j0i10l7.11711j0j15&sourceid=chrome&ie=UTF-8"
  },
  {
    "state": "Haryana",
    "district": "panchkula",
    "hospitalName": " Alchemist Ojas Hospital",
    "hospitalAdress": "Not Available",
    "phoneNo": "8909844444",
    "oxygenBedTotal": 96,
    "oxygenBedOccupied": " 54",
    "oxygenBedAvailable": "42",
    "normalBedTotal": null,
    "normalBedOccupied": " 0",
    "lastUpdatedDate": " 11:13 AM 26th May,21",
    "lastUpdatedTime": " 11:13 AM",
    "googleSearch": "https://www.google.com/search?q=+Alchemist Ojas Hospital+panchkula&rlz=1C1CHBF_enIN859IN859&oq=+Alchemist Ojas Hospital+panchkula&aqs=chrome..69i57j46i10i175i199j0i10l7.11711j0j15&sourceid=chrome&ie=UTF-8"
  },
  {
    "state": "Haryana",
    "district": "panchkula",
    "hospitalName": " Civil Hospital Panchkula",
    "hospitalAdress": "Not Available",
    "phoneNo": "9815111550",
    "oxygenBedTotal": 212,
    "oxygenBedOccupied": " 140",
    "oxygenBedAvailable": "72",
    "normalBedTotal": null,
    "normalBedOccupied": " 31",
    "lastUpdatedDate": " 12:55 PM 26th May,21",
    "lastUpdatedTime": " 12:55 PM",
    "googleSearch": "https://www.google.com/search?q=+Civil Hospital Panchkula+panchkula&rlz=1C1CHBF_enIN859IN859&oq=+Civil Hospital Panchkula+panchkula&aqs=chrome..69i57j46i10i175i199j0i10l7.11711j0j15&sourceid=chrome&ie=UTF-8"
  },
  {
    "state": "Haryana",
    "district": "panchkula",
    "hospitalName": " JN Shory Hospital",
    "hospitalAdress": "Not Available",
    "phoneNo": "9896999660",
    "oxygenBedTotal": 25,
    "oxygenBedOccupied": " 18",
    "oxygenBedAvailable": "7",
    "normalBedTotal": null,
    "normalBedOccupied": " 6",
    "lastUpdatedDate": " 12:27 PM 26th May,21",
    "lastUpdatedTime": " 12:27 PM",
    "googleSearch": "https://www.google.com/search?q=+JN Shory Hospital+panchkula&rlz=1C1CHBF_enIN859IN859&oq=+JN Shory Hospital+panchkula&aqs=chrome..69i57j46i10i175i199j0i10l7.11711j0j15&sourceid=chrome&ie=UTF-8"
  },
  {
    "state": "Haryana",
    "district": "panchkula",
    "hospitalName": " Kare Partners Hospital",
    "hospitalAdress": "Not Available",
    "phoneNo": "8837759149",
    "oxygenBedTotal": 24,
    "oxygenBedOccupied": " 13",
    "oxygenBedAvailable": "11",
    "normalBedTotal": null,
    "normalBedOccupied": " 0",
    "lastUpdatedDate": " 12:26 PM 26th May,21",
    "lastUpdatedTime": " 12:26 PM",
    "googleSearch": "https://www.google.com/search?q=+Kare Partners Hospital+panchkula&rlz=1C1CHBF_enIN859IN859&oq=+Kare Partners Hospital+panchkula&aqs=chrome..69i57j46i10i175i199j0i10l7.11711j0j15&sourceid=chrome&ie=UTF-8"
  },
  {
    "state": "Haryana",
    "district": "panchkula",
    "hospitalName": " Paras Hospital Pvt",
    "hospitalAdress": "Not Available",
    "phoneNo": "01725294444",
    "oxygenBedTotal": 105,
    "oxygenBedOccupied": " 67",
    "oxygenBedAvailable": "38",
    "normalBedTotal": null,
    "normalBedOccupied": " 10",
    "lastUpdatedDate": " 11:08 AM 26th May,21",
    "lastUpdatedTime": " 11:08 AM",
    "googleSearch": "https://www.google.com/search?q=+Paras Hospital Pvt+panchkula&rlz=1C1CHBF_enIN859IN859&oq=+Paras Hospital Pvt+panchkula&aqs=chrome..69i57j46i10i175i199j0i10l7.11711j0j15&sourceid=chrome&ie=UTF-8"
  },
  {
    "state": "Haryana",
    "district": "panchkula",
    "hospitalName": " Wings Hospital",
    "hospitalAdress": "Not Available",
    "phoneNo": "8708830746",
    "oxygenBedTotal": 29,
    "oxygenBedOccupied": " 15",
    "oxygenBedAvailable": "14",
    "normalBedTotal": null,
    "normalBedOccupied": " 11",
    "lastUpdatedDate": " 12:24 PM 26th May,21",
    "lastUpdatedTime": " 12:24 PM",
    "googleSearch": "https://www.google.com/search?q=+Wings Hospital+panchkula&rlz=1C1CHBF_enIN859IN859&oq=+Wings Hospital+panchkula&aqs=chrome..69i57j46i10i175i199j0i10l7.11711j0j15&sourceid=chrome&ie=UTF-8"
  }
]