[
  {
    "state": "Haryana",
    "district": "sirsa",
    "hospitalName": " Apex Hospital, Sirsa",
    "hospitalAdress": "Not Available",
    "phoneNo": "01666226888",
    "oxygenBedTotal": 23,
    "oxygenBedOccupied": " 12",
    "oxygenBedAvailable": "11",
    "normalBedTotal": 2,
    "normalBedOccupied": " 2",
    "normalBedAvailable": "0",
    "lastUpdatedDate": " 5:09 PM 25th May,21",
    "lastUpdatedTime": " 5:09 PM",
    "googleSearch": "https://www.google.com/search?q=+Apex Hospital, Sirsa+sirsa&rlz=1C1CHBF_enIN859IN859&oq=+Apex Hospital, Sirsa+sirsa&aqs=chrome..69i57j46i10i175i199j0i10l7.11711j0j15&sourceid=chrome&ie=UTF-8"
  },
  {
    "state": "Haryana",
    "district": "sirsa",
    "hospitalName": " Astha Hospital, Sirsa",
    "hospitalAdress": "Not Available",
    "phoneNo": "01666222213",
    "oxygenBedTotal": 26,
    "oxygenBedOccupied": " 15",
    "oxygenBedAvailable": "11",
    "normalBedTotal": 0,
    "normalBedOccupied": " 0",
    "normalBedAvailable": "0",
    "lastUpdatedDate": " 5:45 PM 25th May,21",
    "lastUpdatedTime": " 5:45 PM",
    "googleSearch": "https://www.google.com/search?q=+Astha Hospital, Sirsa+sirsa&rlz=1C1CHBF_enIN859IN859&oq=+Astha Hospital, Sirsa+sirsa&aqs=chrome..69i57j46i10i175i199j0i10l7.11711j0j15&sourceid=chrome&ie=UTF-8"
  },
  {
    "state": "Haryana",
    "district": "sirsa",
    "hospitalName": " CIVIL HOSPITAL SIRSA",
    "hospitalAdress": "Not Available",
    "phoneNo": "01666241155",
    "oxygenBedTotal": 95,
    "oxygenBedOccupied": " 85",
    "oxygenBedAvailable": "10",
    "normalBedTotal": 14,
    "normalBedOccupied": " 14",
    "normalBedAvailable": "0",
    "lastUpdatedDate": " 8:38 AM 25th May,21",
    "lastUpdatedTime": " 8:38 AM",
    "googleSearch": "https://www.google.com/search?q=+CIVIL HOSPITAL SIRSA+sirsa&rlz=1C1CHBF_enIN859IN859&oq=+CIVIL HOSPITAL SIRSA+sirsa&aqs=chrome..69i57j46i10i175i199j0i10l7.11711j0j15&sourceid=chrome&ie=UTF-8"
  },
  {
    "state": "Haryana",
    "district": "sirsa",
    "hospitalName": " Dayal Nursing Home, Sirsa",
    "hospitalAdress": "Not Available",
    "phoneNo": "01666221222",
    "oxygenBedTotal": 10,
    "oxygenBedOccupied": " 9",
    "oxygenBedAvailable": "1",
    "normalBedTotal": null,
    "normalBedOccupied": " 3",
    "lastUpdatedDate": " 7:26 PM 25th May,21",
    "lastUpdatedTime": " 7:26 PM",
    "googleSearch": "https://www.google.com/search?q=+Dayal Nursing Home, Sirsa+sirsa&rlz=1C1CHBF_enIN859IN859&oq=+Dayal Nursing Home, Sirsa+sirsa&aqs=chrome..69i57j46i10i175i199j0i10l7.11711j0j15&sourceid=chrome&ie=UTF-8"
  },
  {
    "state": "Haryana",
    "district": "sirsa",
    "hospitalName": " Gupta Hospital, Sirsa",
    "hospitalAdress": "Not Available",
    "phoneNo": "09896024433",
    "oxygenBedTotal": 4,
    "oxygenBedOccupied": " 4",
    "oxygenBedAvailable": "0",
    "normalBedTotal": null,
    "normalBedOccupied": " 3",
    "lastUpdatedDate": " 4:55 PM 25th May,21",
    "lastUpdatedTime": " 4:55 PM",
    "googleSearch": "https://www.google.com/search?q=+Gupta Hospital, Sirsa+sirsa&rlz=1C1CHBF_enIN859IN859&oq=+Gupta Hospital, Sirsa+sirsa&aqs=chrome..69i57j46i10i175i199j0i10l7.11711j0j15&sourceid=chrome&ie=UTF-8"
  },
  {
    "state": "Haryana",
    "district": "sirsa",
    "hospitalName": " Jagdish Nursing Home, Sirsa",
    "hospitalAdress": "Not Available",
    "phoneNo": "9896341418",
    "oxygenBedTotal": 0,
    "oxygenBedOccupied": " 0",
    "oxygenBedAvailable": "0",
    "normalBedTotal": null,
    "normalBedOccupied": " 4",
    "lastUpdatedDate": " 10:01 AM 25th May,21",
    "lastUpdatedTime": " 10:01 AM",
    "googleSearch": "https://www.google.com/search?q=+Jagdish Nursing Home, Sirsa+sirsa&rlz=1C1CHBF_enIN859IN859&oq=+Jagdish Nursing Home, Sirsa+sirsa&aqs=chrome..69i57j46i10i175i199j0i10l7.11711j0j15&sourceid=chrome&ie=UTF-8"
  },
  {
    "state": "Haryana",
    "district": "sirsa",
    "hospitalName": " jCD Hospital, Sirsa",
    "hospitalAdress": "Not Available",
    "phoneNo": "01666241155",
    "oxygenBedTotal": 22,
    "oxygenBedOccupied": " 15",
    "oxygenBedAvailable": "7",
    "normalBedTotal": null,
    "normalBedOccupied": " 35",
    "lastUpdatedDate": " 5:33 PM 25th May,21",
    "lastUpdatedTime": " 5:33 PM",
    "googleSearch": "https://www.google.com/search?q=+jCD Hospital, Sirsa+sirsa&rlz=1C1CHBF_enIN859IN859&oq=+jCD Hospital, Sirsa+sirsa&aqs=chrome..69i57j46i10i175i199j0i10l7.11711j0j15&sourceid=chrome&ie=UTF-8"
  },
  {
    "state": "Haryana",
    "district": "sirsa",
    "hospitalName": " Jeevan Jyoti Hospital, Sirsa",
    "hospitalAdress": "Not Available",
    "phoneNo": "01666231100",
    "oxygenBedTotal": 8,
    "oxygenBedOccupied": " 7",
    "oxygenBedAvailable": "1",
    "normalBedTotal": null,
    "normalBedOccupied": " 1",
    "lastUpdatedDate": " 9:15 AM 25th May,21",
    "lastUpdatedTime": " 9:15 AM",
    "googleSearch": "https://www.google.com/search?q=+Jeevan Jyoti Hospital, Sirsa+sirsa&rlz=1C1CHBF_enIN859IN859&oq=+Jeevan Jyoti Hospital, Sirsa+sirsa&aqs=chrome..69i57j46i10i175i199j0i10l7.11711j0j15&sourceid=chrome&ie=UTF-8"
  },
  {
    "state": "Haryana",
    "district": "sirsa",
    "hospitalName": " Khurana Hospital, Sirsa",
    "hospitalAdress": "Not Available",
    "phoneNo": "01666223003",
    "oxygenBedTotal": 11,
    "oxygenBedOccupied": " 6",
    "oxygenBedAvailable": "5",
    "normalBedTotal": null,
    "normalBedOccupied": " 0",
    "lastUpdatedDate": " 5:18 PM 25th May,21",
    "lastUpdatedTime": " 5:18 PM",
    "googleSearch": "https://www.google.com/search?q=+Khurana Hospital, Sirsa+sirsa&rlz=1C1CHBF_enIN859IN859&oq=+Khurana Hospital, Sirsa+sirsa&aqs=chrome..69i57j46i10i175i199j0i10l7.11711j0j15&sourceid=chrome&ie=UTF-8"
  },
  {
    "state": "Haryana",
    "district": "sirsa",
    "hospitalName": " Lalgarhia Hospital, Sirsa",
    "hospitalAdress": "Not Available",
    "phoneNo": "01666229229",
    "oxygenBedTotal": 13,
    "oxygenBedOccupied": " 13",
    "oxygenBedAvailable": "0",
    "normalBedTotal": null,
    "normalBedOccupied": " 2",
    "lastUpdatedDate": " 4:49 PM 25th May,21",
    "lastUpdatedTime": " 4:49 PM",
    "googleSearch": "https://www.google.com/search?q=+Lalgarhia Hospital, Sirsa+sirsa&rlz=1C1CHBF_enIN859IN859&oq=+Lalgarhia Hospital, Sirsa+sirsa&aqs=chrome..69i57j46i10i175i199j0i10l7.11711j0j15&sourceid=chrome&ie=UTF-8"
  },
  {
    "state": "Haryana",
    "district": "sirsa",
    "hospitalName": " Medicare Hospital, Sirsa",
    "hospitalAdress": "Not Available",
    "phoneNo": "09729260702",
    "oxygenBedTotal": 1,
    "oxygenBedOccupied": " 1",
    "oxygenBedAvailable": "0",
    "normalBedTotal": null,
    "normalBedOccupied": " 6",
    "lastUpdatedDate": " 7:02 PM 25th May,21",
    "lastUpdatedTime": " 7:02 PM",
    "googleSearch": "https://www.google.com/search?q=+Medicare Hospital, Sirsa+sirsa&rlz=1C1CHBF_enIN859IN859&oq=+Medicare Hospital, Sirsa+sirsa&aqs=chrome..69i57j46i10i175i199j0i10l7.11711j0j15&sourceid=chrome&ie=UTF-8"
  },
  {
    "state": "Haryana",
    "district": "sirsa",
    "hospitalName": " Metro Health Care Hospital, Sirsa",
    "hospitalAdress": "Not Available",
    "phoneNo": "01666234666",
    "oxygenBedTotal": 7,
    "oxygenBedOccupied": " 5",
    "oxygenBedAvailable": "2",
    "normalBedTotal": null,
    "normalBedOccupied": " 0",
    "lastUpdatedDate": " 6:12 PM 25th May,21",
    "lastUpdatedTime": " 6:12 PM",
    "googleSearch": "https://www.google.com/search?q=+Metro Health Care Hospital, Sirsa+sirsa&rlz=1C1CHBF_enIN859IN859&oq=+Metro Health Care Hospital, Sirsa+sirsa&aqs=chrome..69i57j46i10i175i199j0i10l7.11711j0j15&sourceid=chrome&ie=UTF-8"
  },
  {
    "state": "Haryana",
    "district": "sirsa",
    "hospitalName": " Mittal Hospital, Sirsa",
    "hospitalAdress": "Not Available",
    "phoneNo": "01666234125",
    "oxygenBedTotal": 25,
    "oxygenBedOccupied": " 14",
    "oxygenBedAvailable": "11",
    "normalBedTotal": null,
    "normalBedOccupied": " 1",
    "lastUpdatedDate": " 5:17 PM 25th May,21",
    "lastUpdatedTime": " 5:17 PM",
    "googleSearch": "https://www.google.com/search?q=+Mittal Hospital, Sirsa+sirsa&rlz=1C1CHBF_enIN859IN859&oq=+Mittal Hospital, Sirsa+sirsa&aqs=chrome..69i57j46i10i175i199j0i10l7.11711j0j15&sourceid=chrome&ie=UTF-8"
  },
  {
    "state": "Haryana",
    "district": "sirsa",
    "hospitalName": " New Life Care Hospital, Sirsa",
    "hospitalAdress": "Not Available",
    "phoneNo": "01666227950",
    "oxygenBedTotal": 9,
    "oxygenBedOccupied": " 7",
    "oxygenBedAvailable": "2",
    "normalBedTotal": null,
    "normalBedOccupied": " 2",
    "lastUpdatedDate": " 4:43 PM 25th May,21",
    "lastUpdatedTime": " 4:43 PM",
    "googleSearch": "https://www.google.com/search?q=+New Life Care Hospital, Sirsa+sirsa&rlz=1C1CHBF_enIN859IN859&oq=+New Life Care Hospital, Sirsa+sirsa&aqs=chrome..69i57j46i10i175i199j0i10l7.11711j0j15&sourceid=chrome&ie=UTF-8"
  },
  {
    "state": "Haryana",
    "district": "sirsa",
    "hospitalName": " Poonia COVID Care Center, Sirsa",
    "hospitalAdress": "Not Available",
    "phoneNo": "09354224747",
    "oxygenBedTotal": 25,
    "oxygenBedOccupied": " 14",
    "oxygenBedAvailable": "11",
    "normalBedTotal": null,
    "normalBedOccupied": " 7",
    "lastUpdatedDate": " 4:27 PM 25th May,21",
    "lastUpdatedTime": " 4:27 PM",
    "googleSearch": "https://www.google.com/search?q=+Poonia COVID Care Center, Sirsa+sirsa&rlz=1C1CHBF_enIN859IN859&oq=+Poonia COVID Care Center, Sirsa+sirsa&aqs=chrome..69i57j46i10i175i199j0i10l7.11711j0j15&sourceid=chrome&ie=UTF-8"
  },
  {
    "state": "Haryana",
    "district": "sirsa",
    "hospitalName": " Sanjeevni Hospital, Sirsa (Wing -2, 1 & 2nd Floor)",
    "hospitalAdress": "Not Available",
    "phoneNo": "01666222221",
    "oxygenBedTotal": 76,
    "oxygenBedOccupied": " 45",
    "oxygenBedAvailable": "31",
    "normalBedTotal": null,
    "normalBedOccupied": " 30",
    "lastUpdatedDate": " 5:42 PM 25th May,21",
    "lastUpdatedTime": " 5:42 PM",
    "googleSearch": "https://www.google.com/search?q=+Sanjeevni Hospital, Sirsa (Wing -2, 1 & 2nd Floor)+sirsa&rlz=1C1CHBF_enIN859IN859&oq=+Sanjeevni Hospital, Sirsa (Wing -2, 1 & 2nd Floor)+sirsa&aqs=chrome..69i57j46i10i175i199j0i10l7.11711j0j15&sourceid=chrome&ie=UTF-8"
  },
  {
    "state": "Haryana",
    "district": "sirsa",
    "hospitalName": " SDCH Dabwali",
    "hospitalAdress": "Not Available",
    "phoneNo": "01668222053",
    "oxygenBedTotal": 15,
    "oxygenBedOccupied": " 12",
    "oxygenBedAvailable": "3",
    "normalBedTotal": null,
    "normalBedOccupied": " 13",
    "lastUpdatedDate": " 5:11 PM 25th May,21",
    "lastUpdatedTime": " 5:11 PM",
    "googleSearch": "https://www.google.com/search?q=+SDCH Dabwali+sirsa&rlz=1C1CHBF_enIN859IN859&oq=+SDCH Dabwali+sirsa&aqs=chrome..69i57j46i10i175i199j0i10l7.11711j0j15&sourceid=chrome&ie=UTF-8"
  },
  {
    "state": "Haryana",
    "district": "sirsa",
    "hospitalName": " Shah Satnam Dera Hospital (Wing -2, 2nd floor), Sirsa",
    "hospitalAdress": "Not Available",
    "phoneNo": "01666260222",
    "oxygenBedTotal": 21,
    "oxygenBedOccupied": " 21",
    "oxygenBedAvailable": "0",
    "normalBedTotal": null,
    "normalBedOccupied": " 30",
    "lastUpdatedDate": " 4:40 PM 25th May,21",
    "lastUpdatedTime": " 4:40 PM",
    "googleSearch": "https://www.google.com/search?q=+Shah Satnam Dera Hospital (Wing -2, 2nd floor), Sirsa+sirsa&rlz=1C1CHBF_enIN859IN859&oq=+Shah Satnam Dera Hospital (Wing -2, 2nd floor), Sirsa+sirsa&aqs=chrome..69i57j46i10i175i199j0i10l7.11711j0j15&sourceid=chrome&ie=UTF-8"
  },
  {
    "state": "Haryana",
    "district": "sirsa",
    "hospitalName": " Shri Baba Tara Hospital & Research Center, Sirsa",
    "hospitalAdress": "Not Available",
    "phoneNo": "",
    "oxygenBedTotal": 15,
    "oxygenBedOccupied": " 15",
    "oxygenBedAvailable": "0",
    "normalBedTotal": null,
    "normalBedOccupied": " 5",
    "lastUpdatedDate": " 4:27 PM 25th May,21",
    "lastUpdatedTime": " 4:27 PM",
    "googleSearch": "https://www.google.com/search?q=+Shri Baba Tara Hospital & Research Center, Sirsa+sirsa&rlz=1C1CHBF_enIN859IN859&oq=+Shri Baba Tara Hospital & Research Center, Sirsa+sirsa&aqs=chrome..69i57j46i10i175i199j0i10l7.11711j0j15&sourceid=chrome&ie=UTF-8"
  },
  {
    "state": "Haryana",
    "district": "sirsa",
    "hospitalName": " SPS Hospital, Sirsa",
    "hospitalAdress": "Not Available",
    "phoneNo": "07504512345",
    "oxygenBedTotal": 18,
    "oxygenBedOccupied": " 12",
    "oxygenBedAvailable": "6",
    "normalBedTotal": null,
    "normalBedOccupied": " 0",
    "lastUpdatedDate": " 4:43 PM 25th May,21",
    "lastUpdatedTime": " 4:43 PM",
    "googleSearch": "https://www.google.com/search?q=+SPS Hospital, Sirsa+sirsa&rlz=1C1CHBF_enIN859IN859&oq=+SPS Hospital, Sirsa+sirsa&aqs=chrome..69i57j46i10i175i199j0i10l7.11711j0j15&sourceid=chrome&ie=UTF-8"
  },
  {
    "state": "Haryana",
    "district": "sirsa",
    "hospitalName": " Suraksha Hospital, Sirsa",
    "hospitalAdress": "Not Available",
    "phoneNo": "01666220020",
    "oxygenBedTotal": 10,
    "oxygenBedOccupied": " 10",
    "oxygenBedAvailable": "0",
    "normalBedTotal": null,
    "normalBedOccupied": " 3",
    "lastUpdatedDate": " 4:30 PM 25th May,21",
    "lastUpdatedTime": " 4:30 PM",
    "googleSearch": "https://www.google.com/search?q=+Suraksha Hospital, Sirsa+sirsa&rlz=1C1CHBF_enIN859IN859&oq=+Suraksha Hospital, Sirsa+sirsa&aqs=chrome..69i57j46i10i175i199j0i10l7.11711j0j15&sourceid=chrome&ie=UTF-8"
  },
  {
    "state": "Haryana",
    "district": "sirsa",
    "hospitalName": " Swastik Hospital, Sirsa",
    "hospitalAdress": "Not Available",
    "phoneNo": "09991330216",
    "oxygenBedTotal": 5,
    "oxygenBedOccupied": " 5",
    "oxygenBedAvailable": "0",
    "normalBedTotal": null,
    "normalBedOccupied": " 5",
    "lastUpdatedDate": " 5:04 PM 25th May,21",
    "lastUpdatedTime": " 5:04 PM",
    "googleSearch": "https://www.google.com/search?q=+Swastik Hospital, Sirsa+sirsa&rlz=1C1CHBF_enIN859IN859&oq=+Swastik Hospital, Sirsa+sirsa&aqs=chrome..69i57j46i10i175i199j0i10l7.11711j0j15&sourceid=chrome&ie=UTF-8"
  },
  {
    "state": "Haryana",
    "district": "sirsa",
    "hospitalName": " Talwar Nursing Home, Sirsa",
    "hospitalAdress": "Not Available",
    "phoneNo": "09896340807",
    "oxygenBedTotal": 12,
    "oxygenBedOccupied": " 12",
    "oxygenBedAvailable": "0",
    "normalBedTotal": null,
    "normalBedOccupied": " 2",
    "lastUpdatedDate": " 5:03 PM 25th May,21",
    "lastUpdatedTime": " 5:03 PM",
    "googleSearch": "https://www.google.com/search?q=+Talwar Nursing Home, Sirsa+sirsa&rlz=1C1CHBF_enIN859IN859&oq=+Talwar Nursing Home, Sirsa+sirsa&aqs=chrome..69i57j46i10i175i199j0i10l7.11711j0j15&sourceid=chrome&ie=UTF-8"
  },
  {
    "state": "Haryana",
    "district": "sirsa",
    "hospitalName": " Tomar Nursing Home, Sirsa",
    "hospitalAdress": "Not Available",
    "phoneNo": "01666233720",
    "oxygenBedTotal": 21,
    "oxygenBedOccupied": " 12",
    "oxygenBedAvailable": "9",
    "normalBedTotal": null,
    "normalBedOccupied": " 2",
    "lastUpdatedDate": " 3:06 PM 25th May,21",
    "lastUpdatedTime": " 3:06 PM",
    "googleSearch": "https://www.google.com/search?q=+Tomar Nursing Home, Sirsa+sirsa&rlz=1C1CHBF_enIN859IN859&oq=+Tomar Nursing Home, Sirsa+sirsa&aqs=chrome..69i57j46i10i175i199j0i10l7.11711j0j15&sourceid=chrome&ie=UTF-8"
  },
  {
    "state": "Haryana",
    "district": "sirsa",
    "hospitalName": " Vardan Hospital, Sirsa",
    "hospitalAdress": "Not Available",
    "phoneNo": "016662339999",
    "oxygenBedTotal": 14,
    "oxygenBedOccupied": " 9",
    "oxygenBedAvailable": "5",
    "normalBedTotal": null,
    "normalBedOccupied": " 3",
    "lastUpdatedDate": " 5:06 PM 25th May,21",
    "lastUpdatedTime": " 5:06 PM",
    "googleSearch": "https://www.google.com/search?q=+Vardan Hospital, Sirsa+sirsa&rlz=1C1CHBF_enIN859IN859&oq=+Vardan Hospital, Sirsa+sirsa&aqs=chrome..69i57j46i10i175i199j0i10l7.11711j0j15&sourceid=chrome&ie=UTF-8"
  }
]